opennano/Results.py
opennano/__init__.py
opennano/io.py
opennano/normalization.py
opennano/qc.py
opennano/run_qc.py
tests/__init__.py
tests/norm_test.py
tests/test_processor.py
tests/test_qc.py
opennano-0.1.2.dist-info/LICENSE
opennano-0.1.2.dist-info/METADATA
opennano-0.1.2.dist-info/WHEEL
opennano-0.1.2.dist-info/top_level.txt
opennano-0.1.2.dist-info/RECORD
